django_filingcabinet-0.0.1.dist-info/METADATA
django_filingcabinet-0.0.1.dist-info/RECORD
django_filingcabinet-0.0.1.dist-info/WHEEL
django_filingcabinet-0.0.1.dist-info/top_level.txt
filingcabinet/__init__.py
filingcabinet/admin.py
filingcabinet/apps.py
filingcabinet/models.py
filingcabinet/pdf_utils.py
filingcabinet/settings.py
filingcabinet/signals.py
filingcabinet/storage.py
filingcabinet/tasks.py
filingcabinet/urls.py
filingcabinet/views.py
filingcabinet/migrations/0001_initial.py
filingcabinet/migrations/0002_documentcollection.py
filingcabinet/migrations/0003_auto_20180810_1559.py
filingcabinet/migrations/0004_auto_20180810_1642.py
filingcabinet/migrations/__init__.py
filingcabinet/static/.DS_Store
filingcabinet/static/filingcabinet/.DS_Store
filingcabinet/static/filingcabinet/admin/pageannotation.js
filingcabinet/static/filingcabinet/dc/print-datauri.css
filingcabinet/static/filingcabinet/dc/print.css
filingcabinet/static/filingcabinet/dc/templates.js
filingcabinet/static/filingcabinet/dc/viewer-datauri.css
filingcabinet/static/filingcabinet/dc/viewer.css
filingcabinet/static/filingcabinet/dc/viewer.js
filingcabinet/static/filingcabinet/viewer/LICENSE
filingcabinet/static/filingcabinet/viewer/build/pdf.js
filingcabinet/static/filingcabinet/viewer/build/pdf.js.map
filingcabinet/static/filingcabinet/viewer/build/pdf.worker.js
filingcabinet/static/filingcabinet/viewer/build/pdf.worker.js.map
filingcabinet/static/filingcabinet/viewer/web/.DS_Store
filingcabinet/static/filingcabinet/viewer/web/viewer.css
filingcabinet/static/filingcabinet/viewer/web/viewer.html
filingcabinet/static/filingcabinet/viewer/web/viewer.js
filingcabinet/static/filingcabinet/viewer/web/cmaps/78-EUC-H.bcmap
filingcabinet/static/filingcabinet/viewer/web/cmaps/78-EUC-V.bcmap
filingcabinet/static/filingcabinet/viewer/web/cmaps/78-H.bcmap
filingcabinet/static/filingcabinet/viewer/web/cmaps/78-RKSJ-H.bcmap
filingcabinet/static/filingcabinet/viewer/web/cmaps/78-RKSJ-V.bcmap
filingcabinet/static/filingcabinet/viewer/web/cmaps/78-V.bcmap
filingcabinet/static/filingcabinet/viewer/web/cmaps/78ms-RKSJ-H.bcmap
